tests/__init__.py
tests/test_cli.py
tests/adapter/__init__.py
tests/adapter/test_cratedb.py
tests/adapter/test_cratedbpg.py
tests/adapter/test_influxdb.py
tests/adapter/test_mongodb.py
tests/adapter/test_mssql.py
tests/adapter/test_postgresql.py
tests/adapter/test_timescaledb.py
tests/adapter/test_timestream.py
tests/read/__init__.py
tests/read/test_tsqt_cli.py
tests/read/test_tsqt_config.py
tests/read/test_tsqt_core.py
tests/util/__init__.py
tests/util/test_batch_size_automator.py
tests/util/test_float_simulator.py
tests/util/test_ticktrack.py
tests/write/__init__.py
tests/write/schema.py
tests/write/test_channel.py
tests/write/test_tsdg_cli.py
tests/write/test_tsdg_config.py
tests/write/test_tsdg_core.py
tsperf/__init__.py
tsperf/cli.py
tsperf/engine.py
tsperf/adapter/__init__.py
tsperf/adapter/cratedb.py
tsperf/adapter/cratedbpg.py
tsperf/adapter/dummy.py
tsperf/adapter/influxdb.py
tsperf/adapter/mongodb.py
tsperf/adapter/mssql.py
tsperf/adapter/postgresql.py
tsperf/adapter/timescaledb.py
tsperf/adapter/timestream.py
tsperf/model/__init__.py
tsperf/model/configuration.py
tsperf/model/interface.py
tsperf/read/__init__.py
tsperf/read/config.py
tsperf/read/core.py
tsperf/schema/__init__.py
tsperf/schema/basic/__init__.py
tsperf/schema/basic/demo.json
tsperf/schema/basic/environment.json
tsperf/schema/basic/motor.json
tsperf/schema/factory/__init__.py
tsperf/schema/factory/complex/__init__.py
tsperf/schema/factory/complex/base1.json
tsperf/schema/factory/complex/base2.json
tsperf/schema/factory/complex/lower.json
tsperf/schema/factory/complex/upper.json
tsperf/schema/factory/simple/__init__.py
tsperf/schema/factory/simple/machine.json
tsperf/util/__init__.py
tsperf/util/common.py
tsperf/util/batch_size_automator/__init__.py
tsperf/util/float_simulator/__init__.py
tsperf/util/tictrack/__init__.py
tsperf/write/__init__.py
tsperf/write/config.py
tsperf/write/core.py
tsperf/write/model/__init__.py
tsperf/write/model/channel.py
tsperf/write/model/metrics.py
tsperf-1.2.1.dist-info/LICENSE
tsperf-1.2.1.dist-info/METADATA
tsperf-1.2.1.dist-info/WHEEL
tsperf-1.2.1.dist-info/entry_points.txt
tsperf-1.2.1.dist-info/top_level.txt
tsperf-1.2.1.dist-info/RECORD
