Metadata-Version: 2.1
Name: tsperf
Version: 1.2.1
Summary: A tool to test performance of time-series databases
Home-page: https://github.com/crate/tsperf
Author: Crate.io
Author-email: office@crate.at
Classifier: Development Status :: 4 - Beta
Classifier: Environment :: Console
Classifier: Intended Audience :: Developers
Classifier: Intended Audience :: Education
Classifier: Intended Audience :: Information Technology
Classifier: Intended Audience :: Science/Research
Classifier: Intended Audience :: System Administrators
Classifier: License :: OSI Approved :: Apache Software License
Classifier: Operating System :: OS Independent
Classifier: Programming Language :: Python :: 3.8
Classifier: Programming Language :: Python :: 3.9
Classifier: Programming Language :: Python :: 3.10
Classifier: Programming Language :: Python :: 3.11
Classifier: Programming Language :: Python :: 3.12
Classifier: Topic :: Communications
Classifier: Topic :: Database
Classifier: Topic :: Scientific/Engineering :: Information Analysis
Classifier: Topic :: Scientific/Engineering :: Interface Engine/Protocol Translator
Classifier: Topic :: Software Development :: Libraries
Classifier: Topic :: Text Processing
Classifier: Topic :: Utilities
Classifier: Operating System :: POSIX
Classifier: Operating System :: Unix
Classifier: Operating System :: MacOS
Requires-Python: >=3.8
License-File: LICENSE
Requires-Dist: blessed <1.21
Requires-Dist: boto3 <1.35
Requires-Dist: crate ==0.35.2
Requires-Dist: prometheus-client <0.11
Requires-Dist: urllib3 <3
Requires-Dist: datetime-truncate <2
Requires-Dist: psycopg2-binary <2.10
Requires-Dist: influxdb-client <2
Requires-Dist: pymongo <5
Requires-Dist: dnspython <3
Requires-Dist: numpy <1.27
Requires-Dist: pgcopy <1.7
Requires-Dist: pyodbc <6
Requires-Dist: tqdm <5
Requires-Dist: cloup <4
Provides-Extra: develop
Requires-Dist: mypy <1.11 ; extra == 'develop'
Requires-Dist: poethepoet <0.27 ; extra == 'develop'
Requires-Dist: pyproject-fmt <1.8 ; extra == 'develop'
Requires-Dist: ruff <0.5 ; extra == 'develop'
Requires-Dist: sphinx-autobuild ==2021.3.14 ; extra == 'develop'
Requires-Dist: validate-pyproject <0.17 ; extra == 'develop'
Provides-Extra: docs
Requires-Dist: furo ; extra == 'docs'
Requires-Dist: myst-parser[linkify] <3,>=0.18 ; extra == 'docs'
Requires-Dist: sphinx <7 ; extra == 'docs'
Requires-Dist: sphinx-copybutton ; extra == 'docs'
Requires-Dist: sphinx-design-elements <1 ; extra == 'docs'
Requires-Dist: sphinxcontrib-mermaid <1 ; extra == 'docs'
Requires-Dist: sphinxext-opengraph <1 ; extra == 'docs'
Provides-Extra: release
Requires-Dist: build <2 ; extra == 'release'
Requires-Dist: twine <6 ; extra == 'release'
Provides-Extra: test
Requires-Dist: dotmap <1.4 ; extra == 'test'
Requires-Dist: pytest <9 ; extra == 'test'
Requires-Dist: pytest-cov <6 ; extra == 'test'
Requires-Dist: ruff <0.5 ; extra == 'test'
